autopack/VERSION
autopack/__init__.py
autopack/__main__.py
autopack/api.py
autopack/cli.py
autopack/errors.py
autopack/filesystem_emulation/__init__.py
autopack/filesystem_emulation/file_manager.py
autopack/filesystem_emulation/filesystem_file_manager.py
autopack/filesystem_emulation/ram_file_manager.py
autopack/filesystem_emulation/workspace_file_manager.py
autopack/get_pack.py
autopack/installation.py
autopack/langchain_wrapper.py
autopack/pack.py
autopack/pack_config.py
autopack/pack_response.py
autopack/prompts.py
autopack/search.py
autopack/selection.py
autopack/utils.py
autopack_tools-0.4.6.dist-info/LICENSE
autopack_tools-0.4.6.dist-info/METADATA
autopack_tools-0.4.6.dist-info/WHEEL
autopack_tools-0.4.6.dist-info/entry_points.txt
autopack_tools-0.4.6.dist-info/RECORD
