Metadata-Version: 2.1
Name: autopack-tools
Version: 0.4.6
Summary: Package Manager for AI Agent tools
Home-page: https://autopack.ai
License: MIT
Author: Erik Peterson
Author-email: e@eriklp.com
Requires-Python: >=3.8.1,<4.0
Classifier: License :: OSI Approved :: MIT License
Classifier: Programming Language :: Python :: 3
Classifier: Programming Language :: Python :: 3.9
Classifier: Programming Language :: Python :: 3.10
Classifier: Programming Language :: Python :: 3.11
Requires-Dist: aiofiles (>=23.1.0,<24.0.0)
Requires-Dist: dataclasses-json (>=0.5.8,<0.6.0)
Requires-Dist: gitpython (>=3.1.31,<4.0.0)
Requires-Dist: langchain (>=0.0.215)
Requires-Dist: requests (>=2.31.0,<3.0.0)
Requires-Dist: types-requests (>=2.31.0.2,<3.0.0.0)
Requires-Dist: urllib3 (>=1.26.16,<2.0.0)
Project-URL: Repository, https://github.com/AutoPackAI/autopack
